linfa/__init__.py
linfa/discrepancy.py
linfa/maf.py
linfa/mlp.py
linfa/nofas.py
linfa/plot_res.py
linfa/run_experiment.py
linfa/run_experiment_mf.py
linfa/transform.py
linfa/models/circuit_models.py
linfa/models/discrepancy_models.py
linfa/models/highdim_models.py
linfa/models/trivial_models.py
linfa/tests/__init__.py
linfa/tests/plot_expected_re.py
linfa/tests/post_process.py
linfa/tests/test_discr_01_onlydiscr.py
linfa/tests/test_discr_02_LF_nodiscr_LFData_TP1.py
linfa/tests/test_discr_03_LF_nodiscr_LFData_TP15.py
linfa/tests/test_discr_04_LF_nodiscr_HFData_TP1.py
linfa/tests/test_discr_05_LF_nodiscr_HFData_TP15.py
linfa/tests/test_discr_06_LF_withdiscr_HFData_TP1.py
linfa/tests/test_discr_07_LF_withdiscr_HFData_TP15.py
linfa/tests/test_linfa.py
linfa/tests/test_prior.py
linfa_vi-1.6.6.dist-info/LICENSE
linfa_vi-1.6.6.dist-info/METADATA
linfa_vi-1.6.6.dist-info/WHEEL
linfa_vi-1.6.6.dist-info/top_level.txt
linfa_vi-1.6.6.dist-info/RECORD
