Metadata-Version: 2.1
Name: linfa_vi
Version: 1.6.6
Summary: A Python library for inference with normalizing flow and annealing
Author-email: resDesLab  <daniele.schiavazzi@gmail.com>
License: Copyright © 2023 <copyright holders>
Project-URL: Homepage, https://github.com/desResLab/LINFA
Keywords: variational inference,normalizig flow,adaptive annealing,physics-based modeling
Classifier: License :: OSI Approved :: MIT License
Classifier: Programming Language :: Python
Classifier: Programming Language :: Python :: 3
Requires-Python: >=3.7
License-File: LICENSE
Requires-Dist: torch ==1.13.1
Requires-Dist: numpy
Requires-Dist: matplotlib
Requires-Dist: ipython
Requires-Dist: coverage
Requires-Dist: tomli ; python_version < "3.11"
Provides-Extra: dev
Requires-Dist: black ; extra == 'dev'
Requires-Dist: bumpver ; extra == 'dev'
Requires-Dist: isort ; extra == 'dev'
Requires-Dist: pip-tools ; extra == 'dev'
Requires-Dist: pytest ; extra == 'dev'
